defcon/__init__.py
defcon/_version.py
defcon/errors.py
defcon/objects/__init__.py
defcon/objects/anchor.py
defcon/objects/base.py
defcon/objects/color.py
defcon/objects/component.py
defcon/objects/contour.py
defcon/objects/dataSet.py
defcon/objects/features.py
defcon/objects/font.py
defcon/objects/glyph.py
defcon/objects/groups.py
defcon/objects/guideline.py
defcon/objects/image.py
defcon/objects/imageSet.py
defcon/objects/info.py
defcon/objects/kerning.py
defcon/objects/layer.py
defcon/objects/layerSet.py
defcon/objects/layoutEngine.py
defcon/objects/lib.py
defcon/objects/point.py
defcon/objects/uniData.py
defcon/pens/__init__.py
defcon/pens/decomposeComponentPointPen.py
defcon/pens/glyphObjectPointPen.py
defcon/pens/reverseContourPointPen.py
defcon/pens/transformPointPen.py
defcon/test/__init__.py
defcon/test/testTools.py
defcon/test/test_errors.py
defcon/test/objects/__init__.py
defcon/test/objects/test_anchor.py
defcon/test/objects/test_base.py
defcon/test/objects/test_color.py
defcon/test/objects/test_component.py
defcon/test/objects/test_contour.py
defcon/test/objects/test_dataSet.py
defcon/test/objects/test_font.py
defcon/test/objects/test_glyph.py
defcon/test/objects/test_groups.py
defcon/test/objects/test_guideline.py
defcon/test/objects/test_image.py
defcon/test/objects/test_imageSet.py
defcon/test/objects/test_info.py
defcon/test/objects/test_kerning.py
defcon/test/objects/test_layer.py
defcon/test/objects/test_layerSet.py
defcon/test/objects/test_uniData.py
defcon/test/objects/test_validation.py
defcon/test/testdata/TestExternalEditing.ufoz
defcon/test/testdata/TestFont.ufoz
defcon/test/testdata/TestContourDirection.ufo/fontinfo.plist
defcon/test/testdata/TestContourDirection.ufo/metainfo.plist
defcon/test/testdata/TestContourDirection.ufo/glyphs/T_estC_ontourD_irection1.glif
defcon/test/testdata/TestContourDirection.ufo/glyphs/T_estC_ontourD_irection2.glif
defcon/test/testdata/TestContourDirection.ufo/glyphs/T_estC_ontourD_irection3.glif
defcon-0.12.0.dist-info/License.txt
defcon-0.12.0.dist-info/METADATA
defcon-0.12.0.dist-info/WHEEL
defcon-0.12.0.dist-info/top_level.txt
defcon-0.12.0.dist-info/zip-safe
defcon-0.12.0.dist-info/RECORD
