Metadata-Version: 2.2
Name: defcon
Version: 0.12.0
Summary: A set of flexible objects for representing UFO data.
Home-page: https://github.com/robotools/defcon
Author: Tal Leming
Author-email: tal@typesupply.com
License: MIT
Classifier: Development Status :: 4 - Beta
Classifier: Intended Audience :: Developers
Classifier: License :: OSI Approved :: MIT License
Classifier: Operating System :: OS Independent
Classifier: Programming Language :: Python
Classifier: Programming Language :: Python :: 3
Classifier: Topic :: Multimedia :: Graphics :: Editors :: Vector-Based
Classifier: Topic :: Software Development :: Libraries :: Python Modules
Requires-Python: >=3.7
License-File: License.txt
Requires-Dist: fonttools[ufo,unicode]>=4.10.0
Provides-Extra: pens
Requires-Dist: fontPens>=0.1.0; extra == "pens"
Provides-Extra: lxml
Requires-Dist: fonttools[lxml]>=4.10.0; extra == "lxml"
Dynamic: author
Dynamic: author-email
Dynamic: classifier
Dynamic: description
Dynamic: home-page
Dynamic: license
Dynamic: provides-extra
Dynamic: requires-dist
Dynamic: requires-python
Dynamic: summary
